setup.py
gui_msg_server/__init__.py
gui_msg_server/server.py
gui_msg_server.egg-info/PKG-INFO
gui_msg_server.egg-info/SOURCES.txt
gui_msg_server.egg-info/dependency_links.txt
gui_msg_server.egg-info/requires.txt
gui_msg_server.egg-info/top_level.txt
gui_msg_server/common/__init__.py
gui_msg_server/common/constants.py
gui_msg_server/common/decorators.py
gui_msg_server/common/descriptors.py
gui_msg_server/common/exceptions.py
gui_msg_server/common/metaclasses.py
gui_msg_server/common/utils.py
gui_msg_server/log/__init__.py
gui_msg_server/log/server_log_config.py
gui_msg_server/server/__init__.py
gui_msg_server/server/add_user.py
gui_msg_server/server/config_window.py
gui_msg_server/server/core.py
gui_msg_server/server/history_window.py
gui_msg_server/server/main_window.py
gui_msg_server/server/remove_user.py
gui_msg_server/server/server_database.py