Metadata-Version: 1.0
Name: gui-msg-server
Version: 0.5.3
Summary: Python GUI Messenger Server
Home-page: UNKNOWN
Author: Vlad Chekunov
Author-email: UNKNOWN
License: UNKNOWN
Platform: UNKNOWN
